metaview/__init__.py
metaview/__main__.py
metaview/app.py
metaview/exiftool.py
metaview/extra_data.py
metaview/location.py
metaview/testing/3dtest.py
metaview/testing/3dtest2.py
metaview/testing/check_extra_data.py
metaview-0.3.1.dist-info/licenses/LICENSE
metaview-0.3.1.dist-info/METADATA
metaview-0.3.1.dist-info/WHEEL
metaview-0.3.1.dist-info/top_level.txt
metaview-0.3.1.dist-info/RECORD
