Metadata-Version: 2.4
Name: MetaView
Version: 0.3.1
Summary: Viewer and Editor for Image Metadata
Author-email: simon0302010 <simon0302010@gmail.com>
License-Expression: GPL-3.0
Project-URL: Homepage, https://github.com/simon0302010/MetaView
Classifier: Operating System :: POSIX :: Linux
Requires-Python: <=3.14,>=3.8
License-File: LICENSE
Requires-Dist: PyQt5
Requires-Dist: reverse_geocoder
Requires-Dist: colorama
Requires-Dist: country-converter
Provides-Extra: test
Requires-Dist: pyopengl; extra == "test"
Requires-Dist: numpy-stl; extra == "test"
Requires-Dist: pyqtgraph; extra == "test"
Dynamic: license-file
